{
  "info": {
    "_postman_id": "62acc6a7-252f-4af3-a381-b41820e85ace",
    "name": "API-CINE Completada",
    "schema": "https://schema.getpostman.com/json/collection/v2.1.0/collection.json",
    "_exporter_id": "44244336",
    "_collection_link": "https://go.postman.co/collection/44244336-62acc6a7-252f-4af3-a381-b41820e85ace?source=collection_link"
  },
  "item": [
    {
      "name": "Auth",
      "item": [
        {
          "name": "Registro",
          "event": [
            {
              "listen": "test",
              "script": {
                "exec": [
                  "pm.test('Status code is 201', function () { pm.response.to.have.status(201); });"
                ],
                "type": "text/javascript"
              }
            }
          ],
          "request": {
            "method": "POST",
            "header": [],
            "body": {
              "mode": "raw",
              "raw": "{\n    \"nombre\": \"Juan\",\n    \"apellido\": \"Perez\",\n    \"email\": \"juan.perez@example.com\",\n    \"password\": \"password123\",\n    \"telefono\": \"12345678\"\n}",
              "options": {
                "raw": {
                  "language": "json"
                }
              }
            },
            "url": {
              "raw": "http://localhost:3000/api/auth/registro",
              "protocol": "http",
              "host": [
                "localhost"
              ],
              "port": "3000",
              "path": [
                "api",
                "auth",
                "registro"
              ]
            }
          },
          "response": []
        },
        {
          "name": "Login",
          "event": [
            {
              "listen": "test",
              "script": {
                "exec": [
                  "pm.test('Status code is 200', function () { pm.response.to.have.status(200); });"
                ],
                "type": "text/javascript"
              }
            }
          ],
          "request": {
            "method": "POST",
            "header": [],
            "body": {
              "mode": "raw",
              "raw": "{\n    \"email\": \"juan.perez@example.com\",\n    \"password\": \"password123\"\n}",
              "options": {
                "raw": {
                  "language": "json"
                }
              }
            },
            "url": {
              "raw": "http://localhost:3000/api/auth/login",
              "protocol": "http",
              "host": [
                "localhost"
              ],
              "port": "3000",
              "path": [
                "api",
                "auth",
                "login"
              ]
            }
          },
          "response": []
        },
        {
          "name": "Me",
          "event": [
            {
              "listen": "test",
              "script": {
                "exec": [
                  "pm.test('Status code is 200', function () { pm.response.to.have.status(200); });"
                ],
                "type": "text/javascript"
              }
            }
          ],
          "request": {
            "method": "GET",
            "header": [],
            "url": {
              "raw": "http://localhost:3000/api/auth/me",
              "protocol": "http",
              "host": [
                "localhost"
              ],
              "port": "3000",
              "path": [
                "api",
                "auth",
                "me"
              ]
            }
          },
          "response": []
        },
        {
          "name": "Actualizar",
          "event": [
            {
              "listen": "test",
              "script": {
                "exec": [
                  "pm.test('Status code is 200', function () { pm.response.to.have.status(200); });"
                ],
                "type": "text/javascript"
              }
            }
          ],
          "request": {
            "method": "PUT",
            "header": [],
            "body": {
              "mode": "raw",
              "raw": "{\n    \"nombre\": \"Juan Modificado\"\n}",
              "options": {
                "raw": {
                  "language": "json"
                }
              }
            },
            "url": {
              "raw": "http://localhost:3000/api/auth/actualizar",
              "protocol": "http",
              "host": [
                "localhost"
              ],
              "port": "3000",
              "path": [
                "api",
                "auth",
                "actualizar"
              ]
            }
          },
          "response": []
        },
        {
          "name": "Cambiar Password",
          "event": [
            {
              "listen": "test",
              "script": {
                "exec": [
                  "pm.test('Status code is 200', function () { pm.response.to.have.status(200); });"
                ],
                "type": "text/javascript"
              }
            }
          ],
          "request": {
            "method": "PUT",
            "header": [],
            "body": {
              "mode": "raw",
              "raw": "{\n    \"passwordActual\": \"password123\",\n    \"nuevaPassword\": \"password1234\"\n}",
              "options": {
                "raw": {
                  "language": "json"
                }
              }
            },
            "url": {
              "raw": "http://localhost:3000/api/auth/cambiar-password",
              "protocol": "http",
              "host": [
                "localhost"
              ],
              "port": "3000",
              "path": [
                "api",
                "auth",
                "cambiar-password"
              ]
            }
          },
          "response": []
        }
      ]
    },
    {
      "name": "Usuarios",
      "item": [
        {
          "name": "Listar Usuarios",
          "event": [
            {
              "listen": "test",
              "script": {
                "exec": [
                  "pm.test('Status code is 200', function () { pm.response.to.have.status(200); });"
                ],
                "type": "text/javascript"
              }
            }
          ],
          "request": {
            "method": "GET",
            "header": [],
            "url": {
              "raw": "http://localhost:3000/api/usuarios",
              "protocol": "http",
              "host": [
                "localhost"
              ],
              "port": "3000",
              "path": [
                "api",
                "usuarios"
              ]
            }
          },
          "response": []
        },
        {
          "name": "Obtener Usuario",
          "event": [
            {
              "listen": "test",
              "script": {
                "exec": [
                  "pm.test('Status code is 200', function () { pm.response.to.have.status(200); });"
                ],
                "type": "text/javascript",
                "packages": {},
                "requests": {}
              }
            }
          ],
          "request": {
            "method": "GET",
            "header": [],
            "url": {
              "raw": "http://localhost:3000/api/usuarios/69bc69d074e763131ccb6263",
              "protocol": "http",
              "host": [
                "localhost"
              ],
              "port": "3000",
              "path": [
                "api",
                "usuarios",
                "69bc69d074e763131ccb6263"
              ]
            }
          },
          "response": []
        },
        {
          "name": "Actualizar Usuario",
          "event": [
            {
              "listen": "test",
              "script": {
                "exec": [
                  "pm.test('Status code is 200', function () { pm.response.to.have.status(200); });"
                ],
                "type": "text/javascript"
              }
            }
          ],
          "request": {
            "method": "PUT",
            "header": [],
            "body": {
              "mode": "raw",
              "raw": "{\n    \"rol\": \"admin\"\n}",
              "options": {
                "raw": {
                  "language": "json"
                }
              }
            },
            "url": {
              "raw": "http://localhost:3000/api/usuarios/ID_AQUI",
              "protocol": "http",
              "host": [
                "localhost"
              ],
              "port": "3000",
              "path": [
                "api",
                "usuarios",
                "ID_AQUI"
              ]
            }
          },
          "response": []
        },
        {
          "name": "Desactivar Usuario",
          "event": [
            {
              "listen": "test",
              "script": {
                "exec": [
                  "pm.test('Status code is 200', function () { pm.response.to.have.status(200); });"
                ],
                "type": "text/javascript"
              }
            }
          ],
          "request": {
            "method": "DELETE",
            "header": [],
            "url": {
              "raw": "http://localhost:3000/api/usuarios/ID_AQUI",
              "protocol": "http",
              "host": [
                "localhost"
              ],
              "port": "3000",
              "path": [
                "api",
                "usuarios",
                "ID_AQUI"
              ]
            }
          },
          "response": []
        }
      ]
    },
    {
      "name": "Salas",
      "item": [
        {
          "name": "Listar Salas",
          "event": [
            {
              "listen": "test",
              "script": {
                "exec": [
                  "pm.test('Status code is 200', function () { pm.response.to.have.status(200); });"
                ],
                "type": "text/javascript"
              }
            }
          ],
          "request": {
            "method": "GET",
            "header": [],
            "url": {
              "raw": "http://localhost:3000/api/salas",
              "protocol": "http",
              "host": [
                "localhost"
              ],
              "port": "3000",
              "path": [
                "api",
                "salas"
              ]
            }
          },
          "response": []
        },
        {
          "name": "Crear Sala",
          "event": [
            {
              "listen": "test",
              "script": {
                "exec": [
                  "pm.test('Status code is 201', function () { pm.response.to.have.status(201); });"
                ],
                "type": "text/javascript",
                "packages": {},
                "requests": {}
              }
            }
          ],
          "request": {
            "method": "POST",
            "header": [],
            "body": {
              "mode": "raw",
              "raw": "{\n    \"nombre\": \"Sala 2\",\n    \"capacidad\": 50,\n    \"tipo\": \"2D\"\n}",
              "options": {
                "raw": {
                  "language": "json"
                }
              }
            },
            "url": {
              "raw": "http://localhost:3000/api/salas",
              "protocol": "http",
              "host": [
                "localhost"
              ],
              "port": "3000",
              "path": [
                "api",
                "salas"
              ]
            }
          },
          "response": []
        },
        {
          "name": "Obtener Sala",
          "event": [
            {
              "listen": "test",
              "script": {
                "exec": [
                  "pm.test('Status code is 200', function () { pm.response.to.have.status(200); });"
                ],
                "type": "text/javascript"
              }
            }
          ],
          "request": {
            "method": "GET",
            "header": [],
            "url": {
              "raw": "http://localhost:3000/api/salas/ID_AQUI",
              "protocol": "http",
              "host": [
                "localhost"
              ],
              "port": "3000",
              "path": [
                "api",
                "salas",
                "ID_AQUI"
              ]
            }
          },
          "response": []
        },
        {
          "name": "Actualizar Sala",
          "event": [
            {
              "listen": "test",
              "script": {
                "exec": [
                  "pm.test('Status code is 200', function () { pm.response.to.have.status(200); });"
                ],
                "type": "text/javascript",
                "packages": {},
                "requests": {}
              }
            }
          ],
          "request": {
            "method": "PUT",
            "header": [],
            "body": {
              "mode": "raw",
              "raw": "{\n    \"capacidad\": 60\n}",
              "options": {
                "raw": {
                  "language": "json"
                }
              }
            },
            "url": {
              "raw": "http://localhost:3000/api/salas/69bc6a3774e763131ccb626e",
              "protocol": "http",
              "host": [
                "localhost"
              ],
              "port": "3000",
              "path": [
                "api",
                "salas",
                "69bc6a3774e763131ccb626e"
              ]
            }
          },
          "response": []
        },
        {
          "name": "Eliminar Sala",
          "event": [
            {
              "listen": "test",
              "script": {
                "exec": [
                  "pm.test('Status code is 200', function () { pm.response.to.have.status(200); });"
                ],
                "type": "text/javascript"
              }
            }
          ],
          "request": {
            "method": "DELETE",
            "header": [],
            "url": {
              "raw": "http://localhost:3000/api/salas/ID_AQUI",
              "protocol": "http",
              "host": [
                "localhost"
              ],
              "port": "3000",
              "path": [
                "api",
                "salas",
                "ID_AQUI"
              ]
            }
          },
          "response": []
        }
      ]
    },
    {
      "name": "Peliculas",
      "item": [
        {
          "name": "Listar Peliculas",
          "event": [
            {
              "listen": "test",
              "script": {
                "exec": [
                  "pm.test('Status code is 200', function () { pm.response.to.have.status(200); });"
                ],
                "type": "text/javascript"
              }
            }
          ],
          "request": {
            "method": "GET",
            "header": [],
            "url": {
              "raw": "http://localhost:3000/api/peliculas",
              "protocol": "http",
              "host": [
                "localhost"
              ],
              "port": "3000",
              "path": [
                "api",
                "peliculas"
              ]
            }
          },
          "response": []
        },
        {
          "name": "Cartelera",
          "event": [
            {
              "listen": "test",
              "script": {
                "exec": [
                  "pm.test('Status code is 200', function () { pm.response.to.have.status(200); });"
                ],
                "type": "text/javascript"
              }
            }
          ],
          "request": {
            "method": "GET",
            "header": [],
            "url": {
              "raw": "http://localhost:3000/api/peliculas/cartelera",
              "protocol": "http",
              "host": [
                "localhost"
              ],
              "port": "3000",
              "path": [
                "api",
                "peliculas",
                "cartelera"
              ]
            }
          },
          "response": []
        },
        {
          "name": "Proximos Estrenos",
          "event": [
            {
              "listen": "test",
              "script": {
                "exec": [
                  "pm.test('Status code is 200', function () { pm.response.to.have.status(200); });"
                ],
                "type": "text/javascript"
              }
            }
          ],
          "request": {
            "method": "GET",
            "header": [],
            "url": {
              "raw": "http://localhost:3000/api/peliculas/proximos-estrenos",
              "protocol": "http",
              "host": [
                "localhost"
              ],
              "port": "3000",
              "path": [
                "api",
                "peliculas",
                "proximos-estrenos"
              ]
            }
          },
          "response": []
        },
        {
          "name": "Crear Pelicula",
          "event": [
            {
              "listen": "test",
              "script": {
                "exec": [
                  "pm.test('Status code is 201', function () { pm.response.to.have.status(201); });"
                ],
                "type": "text/javascript",
                "packages": {},
                "requests": {}
              }
            }
          ],
          "request": {
            "method": "POST",
            "header": [],
            "body": {
              "mode": "raw",
              "raw": "{\n    \"titulo\": \"Dune: Parte Dos\",\n    \"sinopsis\": \"Paul Atreides se une a Chani y a los Fremen mientras busca venganza contra los conspiradores que destruyeron a su familia.\",\n    \"duracion_min\": 166,\n    \"generos\": [\"Ciencia Ficción\", \"Aventura\", \"Drama\"],\n    \"idioma\": \"Español Latino\",\n    \"clasificacion\": \"PG-13\",\n    \"director\": \"Denis Villeneuve\",\n    \"actores\": [\"Timothée Chalamet\", \"Zendaya\", \"Rebecca Ferguson\"],\n    \"poster_url\": \"https://midominio.com/poster/dune-2.jpg\",\n    \"fecha_estreno\": \"2026-04-19T00:00:00.000Z\"\n}",
              "options": {
                "raw": {
                  "language": "json"
                }
              }
            },
            "url": {
              "raw": "http://localhost:3000/api/peliculas",
              "protocol": "http",
              "host": [
                "localhost"
              ],
              "port": "3000",
              "path": [
                "api",
                "peliculas"
              ]
            }
          },
          "response": []
        },
        {
          "name": "Obtener Pelicula",
          "event": [
            {
              "listen": "test",
              "script": {
                "exec": [
                  "pm.test('Status code is 200', function () { pm.response.to.have.status(200); });"
                ],
                "type": "text/javascript"
              }
            }
          ],
          "request": {
            "method": "GET",
            "header": [],
            "url": {
              "raw": "http://localhost:3000/api/peliculas/ID_AQUI",
              "protocol": "http",
              "host": [
                "localhost"
              ],
              "port": "3000",
              "path": [
                "api",
                "peliculas",
                "ID_AQUI"
              ]
            }
          },
          "response": []
        },
        {
          "name": "Actualizar Pelicula",
          "event": [
            {
              "listen": "test",
              "script": {
                "exec": [
                  "pm.test('Status code is 200', function () { pm.response.to.have.status(200); });"
                ],
                "type": "text/javascript"
              }
            }
          ],
          "request": {
            "method": "PUT",
            "header": [],
            "body": {
              "mode": "raw",
              "raw": "{\n    \"titulo\": \"Movie Updated\"\n}",
              "options": {
                "raw": {
                  "language": "json"
                }
              }
            },
            "url": {
              "raw": "http://localhost:3000/api/peliculas/ID_AQUI",
              "protocol": "http",
              "host": [
                "localhost"
              ],
              "port": "3000",
              "path": [
                "api",
                "peliculas",
                "ID_AQUI"
              ]
            }
          },
          "response": []
        },
        {
          "name": "Desactivar Pelicula",
          "event": [
            {
              "listen": "test",
              "script": {
                "exec": [
                  "pm.test('Status code is 200', function () { pm.response.to.have.status(200); });"
                ],
                "type": "text/javascript"
              }
            }
          ],
          "request": {
            "method": "DELETE",
            "header": [],
            "url": {
              "raw": "http://localhost:3000/api/peliculas/ID_AQUI",
              "protocol": "http",
              "host": [
                "localhost"
              ],
              "port": "3000",
              "path": [
                "api",
                "peliculas",
                "ID_AQUI"
              ]
            }
          },
          "response": []
        }
      ]
    },
    {
      "name": "Asientos",
      "item": [
        {
          "name": "Asientos por Sala",
          "event": [
            {
              "listen": "test",
              "script": {
                "exec": [
                  "pm.test('Status code is 200', function () { pm.response.to.have.status(200); });"
                ],
                "type": "text/javascript",
                "packages": {},
                "requests": {}
              }
            }
          ],
          "request": {
            "method": "GET",
            "header": [],
            "url": {
              "raw": "http://localhost:3000/api/asientos/sala/69bc6cffabaefb3b79b24128",
              "protocol": "http",
              "host": [
                "localhost"
              ],
              "port": "3000",
              "path": [
                "api",
                "asientos",
                "sala",
                "69bc6cffabaefb3b79b24128"
              ]
            }
          },
          "response": []
        },
        {
          "name": "Crear Asiento",
          "event": [
            {
              "listen": "test",
              "script": {
                "exec": [
                  "pm.test('Status code is 201', function () { pm.response.to.have.status(201); });"
                ],
                "type": "text/javascript"
              }
            }
          ],
          "request": {
            "method": "POST",
            "header": [],
            "body": {
              "mode": "raw",
              "raw": "{\n    \"sala\": \"SALA_ID\",\n    \"fila\": \"A\",\n    \"numero\": 1,\n    \"tipo\": \"Normal\"\n}",
              "options": {
                "raw": {
                  "language": "json"
                }
              }
            },
            "url": {
              "raw": "http://localhost:3000/api/asientos",
              "protocol": "http",
              "host": [
                "localhost"
              ],
              "port": "3000",
              "path": [
                "api",
                "asientos"
              ]
            }
          },
          "response": []
        },
        {
          "name": "Crear Multiples Asientos",
          "event": [
            {
              "listen": "test",
              "script": {
                "exec": [
                  "pm.test('Status code is 201', function () { pm.response.to.have.status(201); });"
                ],
                "type": "text/javascript",
                "packages": {},
                "requests": {}
              }
            }
          ],
          "request": {
            "method": "POST",
            "header": [],
            "body": {
              "mode": "raw",
              "raw": "{ \n    \"sala_id\": \"69bc6cffabaefb3b79b24128\", \n    \"filas\": \"A,B,C,D,E\", \n    \"asientosPorFila\": 10,\n    \"tipo\": \"normal\"\n}",
              "options": {
                "raw": {
                  "language": "json"
                }
              }
            },
            "url": {
              "raw": "http://localhost:3000/api/asientos/bulk",
              "protocol": "http",
              "host": [
                "localhost"
              ],
              "port": "3000",
              "path": [
                "api",
                "asientos",
                "bulk"
              ]
            }
          },
          "response": []
        },
        {
          "name": "Obtener Asiento",
          "event": [
            {
              "listen": "test",
              "script": {
                "exec": [
                  "pm.test('Status code is 200', function () { pm.response.to.have.status(200); });"
                ],
                "type": "text/javascript",
                "packages": {},
                "requests": {}
              }
            }
          ],
          "request": {
            "method": "GET",
            "header": [],
            "url": {
              "raw": "http://localhost:3000/api/asientos/69bc6d12abaefb3b79b2412c",
              "protocol": "http",
              "host": [
                "localhost"
              ],
              "port": "3000",
              "path": [
                "api",
                "asientos",
                "69bc6d12abaefb3b79b2412c"
              ]
            }
          },
          "response": []
        },
        {
          "name": "Actualizar Asiento",
          "event": [
            {
              "listen": "test",
              "script": {
                "exec": [
                  "pm.test('Status code is 200', function () { pm.response.to.have.status(200); });"
                ],
                "type": "text/javascript"
              }
            }
          ],
          "request": {
            "method": "PUT",
            "header": [],
            "body": {
              "mode": "raw",
              "raw": "{\n    \"estado\": \"Mantenimiento\"\n}",
              "options": {
                "raw": {
                  "language": "json"
                }
              }
            },
            "url": {
              "raw": "http://localhost:3000/api/asientos/ID_AQUI",
              "protocol": "http",
              "host": [
                "localhost"
              ],
              "port": "3000",
              "path": [
                "api",
                "asientos",
                "ID_AQUI"
              ]
            }
          },
          "response": []
        },
        {
          "name": "Eliminar Asiento",
          "event": [
            {
              "listen": "test",
              "script": {
                "exec": [
                  "pm.test('Status code is 200', function () { pm.response.to.have.status(200); });"
                ],
                "type": "text/javascript"
              }
            }
          ],
          "request": {
            "method": "DELETE",
            "header": [],
            "url": {
              "raw": "http://localhost:3000/api/asientos/ID_AQUI",
              "protocol": "http",
              "host": [
                "localhost"
              ],
              "port": "3000",
              "path": [
                "api",
                "asientos",
                "ID_AQUI"
              ]
            }
          },
          "response": []
        }
      ]
    },
    {
      "name": "Funciones",
      "item": [
        {
          "name": "Listar Funciones",
          "event": [
            {
              "listen": "test",
              "script": {
                "exec": [
                  "pm.test('Status code is 200', function () { pm.response.to.have.status(200); });"
                ],
                "type": "text/javascript"
              }
            }
          ],
          "request": {
            "method": "GET",
            "header": [],
            "url": {
              "raw": "http://localhost:3000/api/funciones",
              "protocol": "http",
              "host": [
                "localhost"
              ],
              "port": "3000",
              "path": [
                "api",
                "funciones"
              ]
            }
          },
          "response": []
        },
        {
          "name": "Funciones por Pelicula",
          "event": [
            {
              "listen": "test",
              "script": {
                "exec": [
                  "pm.test('Status code is 200', function () { pm.response.to.have.status(200); });"
                ],
                "type": "text/javascript",
                "packages": {},
                "requests": {}
              }
            }
          ],
          "request": {
            "method": "GET",
            "header": [],
            "url": {
              "raw": "http://localhost:3000/api/funciones/pelicula/69bc6b8d74e763131ccb6287",
              "protocol": "http",
              "host": [
                "localhost"
              ],
              "port": "3000",
              "path": [
                "api",
                "funciones",
                "pelicula",
                "69bc6b8d74e763131ccb6287"
              ]
            }
          },
          "response": []
        },
        {
          "name": "Crear Funcion",
          "event": [
            {
              "listen": "test",
              "script": {
                "exec": [
                  "pm.test('Status code is 201', function () { pm.response.to.have.status(201); });"
                ],
                "type": "text/javascript",
                "packages": {},
                "requests": {}
              }
            }
          ],
          "request": {
            "method": "POST",
            "header": [],
            "body": {
              "mode": "raw",
              "raw": "{\n    \"pelicula_id\": \"69bc6b8d74e763131ccb6287\",\n    \"sala_id\": \"69bc6cffabaefb3b79b24128\",\n    \"fecha_hora\": \"2026-12-31T20:00:00.000Z\",\n    \"precio_base\": 50\n}",
              "options": {
                "raw": {
                  "language": "json"
                }
              }
            },
            "url": {
              "raw": "http://localhost:3000/api/funciones",
              "protocol": "http",
              "host": [
                "localhost"
              ],
              "port": "3000",
              "path": [
                "api",
                "funciones"
              ]
            }
          },
          "response": []
        },
        {
          "name": "Obtener Funcion",
          "event": [
            {
              "listen": "test",
              "script": {
                "exec": [
                  "pm.test('Status code is 200', function () { pm.response.to.have.status(200); });"
                ],
                "type": "text/javascript",
                "packages": {},
                "requests": {}
              }
            }
          ],
          "request": {
            "method": "GET",
            "header": [],
            "url": {
              "raw": "http://localhost:3000/api/funciones/69bc6dbeabaefb3b79b24168",
              "protocol": "http",
              "host": [
                "localhost"
              ],
              "port": "3000",
              "path": [
                "api",
                "funciones",
                "69bc6dbeabaefb3b79b24168"
              ]
            }
          },
          "response": []
        },
        {
          "name": "Actualizar Funcion",
          "event": [
            {
              "listen": "test",
              "script": {
                "exec": [
                  "pm.test('Status code is 200', function () { pm.response.to.have.status(200); });"
                ],
                "type": "text/javascript"
              }
            }
          ],
          "request": {
            "method": "PUT",
            "header": [],
            "body": {
              "mode": "raw",
              "raw": "{\n    \"precio\": 55\n}",
              "options": {
                "raw": {
                  "language": "json"
                }
              }
            },
            "url": {
              "raw": "http://localhost:3000/api/funciones/ID_AQUI",
              "protocol": "http",
              "host": [
                "localhost"
              ],
              "port": "3000",
              "path": [
                "api",
                "funciones",
                "ID_AQUI"
              ]
            }
          },
          "response": []
        },
        {
          "name": "Eliminar Funcion",
          "event": [
            {
              "listen": "test",
              "script": {
                "exec": [
                  "pm.test('Status code is 200', function () { pm.response.to.have.status(200); });"
                ],
                "type": "text/javascript"
              }
            }
          ],
          "request": {
            "method": "DELETE",
            "header": [],
            "url": {
              "raw": "http://localhost:3000/api/funciones/ID_AQUI",
              "protocol": "http",
              "host": [
                "localhost"
              ],
              "port": "3000",
              "path": [
                "api",
                "funciones",
                "ID_AQUI"
              ]
            }
          },
          "response": []
        }
      ]
    },
    {
      "name": "Reservas",
      "item": [
        {
          "name": "Asientos Disponibles",
          "event": [
            {
              "listen": "test",
              "script": {
                "exec": [
                  "pm.test('Status code is 200', function () { pm.response.to.have.status(200); });"
                ],
                "type": "text/javascript"
              }
            }
          ],
          "request": {
            "method": "GET",
            "header": [],
            "url": {
              "raw": "http://localhost:3000/api/reservas/asientos-disponibles/FUNCION_ID",
              "protocol": "http",
              "host": [
                "localhost"
              ],
              "port": "3000",
              "path": [
                "api",
                "reservas",
                "asientos-disponibles",
                "FUNCION_ID"
              ]
            }
          },
          "response": []
        },
        {
          "name": "Mis Reservas",
          "event": [
            {
              "listen": "test",
              "script": {
                "exec": [
                  "pm.test('Status code is 200', function () { pm.response.to.have.status(200); });"
                ],
                "type": "text/javascript"
              }
            }
          ],
          "request": {
            "method": "GET",
            "header": [],
            "url": {
              "raw": "http://localhost:3000/api/reservas/mis-reservas",
              "protocol": "http",
              "host": [
                "localhost"
              ],
              "port": "3000",
              "path": [
                "api",
                "reservas",
                "mis-reservas"
              ]
            }
          },
          "response": []
        },
        {
          "name": "Crear Reserva",
          "event": [
            {
              "listen": "test",
              "script": {
                "exec": [
                  "pm.test('Status code is 201', function () { pm.response.to.have.status(201); });"
                ],
                "type": "text/javascript",
                "packages": {},
                "requests": {}
              }
            }
          ],
          "request": {
            "method": "POST",
            "header": [],
            "body": {
              "mode": "raw",
              "raw": "{\n    \"funcion_id\": \"69bc6dbeabaefb3b79b24168\",\n    \"asientos_ids\": [\n        \"69bc6d12abaefb3b79b2412c\"\n       \n    ]\n}",
              "options": {
                "raw": {
                  "language": "json"
                }
              }
            },
            "url": {
              "raw": "http://localhost:3000/api/reservas",
              "protocol": "http",
              "host": [
                "localhost"
              ],
              "port": "3000",
              "path": [
                "api",
                "reservas"
              ]
            }
          },
          "response": []
        },
        {
          "name": "Listar Todas Reservas",
          "event": [
            {
              "listen": "test",
              "script": {
                "exec": [
                  "pm.test('Status code is 200', function () { pm.response.to.have.status(200); });"
                ],
                "type": "text/javascript"
              }
            }
          ],
          "request": {
            "method": "GET",
            "header": [],
            "url": {
              "raw": "http://localhost:3000/api/reservas",
              "protocol": "http",
              "host": [
                "localhost"
              ],
              "port": "3000",
              "path": [
                "api",
                "reservas"
              ]
            }
          },
          "response": []
        },
        {
          "name": "Obtener Reserva",
          "event": [
            {
              "listen": "test",
              "script": {
                "exec": [
                  "pm.test('Status code is 200', function () { pm.response.to.have.status(200); });"
                ],
                "type": "text/javascript"
              }
            }
          ],
          "request": {
            "method": "GET",
            "header": [],
            "url": {
              "raw": "http://localhost:3000/api/reservas/ID_AQUI",
              "protocol": "http",
              "host": [
                "localhost"
              ],
              "port": "3000",
              "path": [
                "api",
                "reservas",
                "ID_AQUI"
              ]
            }
          },
          "response": []
        },
        {
          "name": "Actualizar Estado Reserva (Admin)",
          "event": [
            {
              "listen": "test",
              "script": {
                "exec": [
                  "pm.test('Status code is 200', function () { pm.response.to.have.status(200); });"
                ],
                "type": "text/javascript"
              }
            }
          ],
          "request": {
            "method": "PUT",
            "header": [],
            "body": {
              "mode": "raw",
              "raw": "{\n    \"estado\": \"Cancelada\"\n}",
              "options": {
                "raw": {
                  "language": "json"
                }
              }
            },
            "url": {
              "raw": "http://localhost:3000/api/reservas/ID_AQUI",
              "protocol": "http",
              "host": [
                "localhost"
              ],
              "port": "3000",
              "path": [
                "api",
                "reservas",
                "ID_AQUI"
              ]
            }
          },
          "response": []
        }
      ]
    },
    {
      "name": "Pagos",
      "item": [
        {
          "name": "Mis Pagos",
          "event": [
            {
              "listen": "test",
              "script": {
                "exec": [
                  "pm.test('Status code is 200', function () { pm.response.to.have.status(200); });"
                ],
                "type": "text/javascript"
              }
            }
          ],
          "request": {
            "method": "GET",
            "header": [],
            "url": {
              "raw": "http://localhost:3000/api/pagos/mis-pagos",
              "protocol": "http",
              "host": [
                "localhost"
              ],
              "port": "3000",
              "path": [
                "api",
                "pagos",
                "mis-pagos"
              ]
            }
          },
          "response": []
        },
        {
          "name": "Procesar Pago",
          "event": [
            {
              "listen": "test",
              "script": {
                "exec": [
                  "pm.test('Status code is 201', function () { pm.response.to.have.status(201); });"
                ],
                "type": "text/javascript",
                "packages": {},
                "requests": {}
              }
            }
          ],
          "request": {
            "method": "POST",
            "header": [],
            "body": {
              "mode": "raw",
              "raw": "{\n    \"reserva_id\": \"69bc6e73abaefb3b79b2417a\",\n    \"metodo_pago\": \"paypal\"\n}",
              "options": {
                "raw": {
                  "language": "json"
                }
              }
            },
            "url": {
              "raw": "http://localhost:3000/api/pagos",
              "protocol": "http",
              "host": [
                "localhost"
              ],
              "port": "3000",
              "path": [
                "api",
                "pagos"
              ]
            }
          },
          "response": []
        },
        {
          "name": "Listar Todos Pagos",
          "event": [
            {
              "listen": "test",
              "script": {
                "exec": [
                  "pm.test('Status code is 200', function () { pm.response.to.have.status(200); });"
                ],
                "type": "text/javascript"
              }
            }
          ],
          "request": {
            "method": "GET",
            "header": [],
            "url": {
              "raw": "http://localhost:3000/api/pagos",
              "protocol": "http",
              "host": [
                "localhost"
              ],
              "port": "3000",
              "path": [
                "api",
                "pagos"
              ]
            }
          },
          "response": []
        },
        {
          "name": "Obtener Pago",
          "event": [
            {
              "listen": "test",
              "script": {
                "exec": [
                  "pm.test('Status code is 200', function () { pm.response.to.have.status(200); });"
                ],
                "type": "text/javascript",
                "packages": {},
                "requests": {}
              }
            }
          ],
          "request": {
            "method": "GET",
            "header": [],
            "url": {
              "raw": "http://localhost:3000/api/pagos/69bc6ee2abaefb3b79b24189",
              "protocol": "http",
              "host": [
                "localhost"
              ],
              "port": "3000",
              "path": [
                "api",
                "pagos",
                "69bc6ee2abaefb3b79b24189"
              ]
            }
          },
          "response": []
        },
        {
          "name": "Solicitar Reembolso",
          "event": [
            {
              "listen": "test",
              "script": {
                "exec": [
                  "pm.test('Status code is 200', function () { pm.response.to.have.status(200); });"
                ],
                "type": "text/javascript",
                "packages": {},
                "requests": {}
              }
            }
          ],
          "request": {
            "method": "POST",
            "header": [],
            "url": {
              "raw": "http://localhost:3000/api/pagos/69bc6ee2abaefb3b79b24189/reembolso",
              "protocol": "http",
              "host": [
                "localhost"
              ],
              "port": "3000",
              "path": [
                "api",
                "pagos",
                "69bc6ee2abaefb3b79b24189",
                "reembolso"
              ]
            }
          },
          "response": []
        }
      ]
    },
    {
      "name": "Snacks",
      "item": [
        {
          "name": "Listar Snacks",
          "event": [
            {
              "listen": "test",
              "script": {
                "exec": [
                  "pm.test('Status code is 200', function () { pm.response.to.have.status(200); });"
                ],
                "type": "text/javascript"
              }
            }
          ],
          "request": {
            "method": "GET",
            "header": [],
            "url": {
              "raw": "http://localhost:3000/api/snacks",
              "protocol": "http",
              "host": [
                "localhost"
              ],
              "port": "3000",
              "path": [
                "api",
                "snacks"
              ]
            }
          },
          "response": []
        },
        {
          "name": "Crear Snack",
          "event": [
            {
              "listen": "test",
              "script": {
                "exec": [
                  "pm.test('Status code is 201', function () { pm.response.to.have.status(201); });"
                ],
                "type": "text/javascript",
                "packages": {},
                "requests": {}
              }
            }
          ],
          "request": {
            "method": "POST",
            "header": [],
            "body": {
              "mode": "raw",
              "raw": "{\n    \"nombre\": \"Palomitas\",\n    \"descripcion\": \"Palomitas grandes\",\n    \"precio\": 5.5,\n    \"categoria\": \"palomitas\",\n    \"stock\": 100\n}",
              "options": {
                "raw": {
                  "language": "json"
                }
              }
            },
            "url": {
              "raw": "http://localhost:3000/api/snacks",
              "protocol": "http",
              "host": [
                "localhost"
              ],
              "port": "3000",
              "path": [
                "api",
                "snacks"
              ]
            }
          },
          "response": []
        },
        {
          "name": "Obtener Snack",
          "event": [
            {
              "listen": "test",
              "script": {
                "exec": [
                  "pm.test('Status code is 200', function () { pm.response.to.have.status(200); });"
                ],
                "type": "text/javascript",
                "packages": {},
                "requests": {}
              }
            }
          ],
          "request": {
            "method": "GET",
            "header": [],
            "url": {
              "raw": "http://localhost:3000/api/snacks/69bc6f52abaefb3b79b2419f",
              "protocol": "http",
              "host": [
                "localhost"
              ],
              "port": "3000",
              "path": [
                "api",
                "snacks",
                "69bc6f52abaefb3b79b2419f"
              ]
            }
          },
          "response": []
        },
        {
          "name": "Actualizar Snack",
          "event": [
            {
              "listen": "test",
              "script": {
                "exec": [
                  "pm.test('Status code is 200', function () { pm.response.to.have.status(200); });"
                ],
                "type": "text/javascript"
              }
            }
          ],
          "request": {
            "method": "PUT",
            "header": [],
            "body": {
              "mode": "raw",
              "raw": "{\n    \"precio\": 6\n}",
              "options": {
                "raw": {
                  "language": "json"
                }
              }
            },
            "url": {
              "raw": "http://localhost:3000/api/snacks/ID_AQUI",
              "protocol": "http",
              "host": [
                "localhost"
              ],
              "port": "3000",
              "path": [
                "api",
                "snacks",
                "ID_AQUI"
              ]
            }
          },
          "response": []
        },
        {
          "name": "Eliminar Snack",
          "event": [
            {
              "listen": "test",
              "script": {
                "exec": [
                  "pm.test('Status code is 200', function () { pm.response.to.have.status(200); });"
                ],
                "type": "text/javascript"
              }
            }
          ],
          "request": {
            "method": "DELETE",
            "header": [],
            "url": {
              "raw": "http://localhost:3000/api/snacks/ID_AQUI",
              "protocol": "http",
              "host": [
                "localhost"
              ],
              "port": "3000",
              "path": [
                "api",
                "snacks",
                "ID_AQUI"
              ]
            }
          },
          "response": []
        }
      ]
    },
    {
      "name": "Pedidos Snacks",
      "item": [
        {
          "name": "Mis Pedidos",
          "event": [
            {
              "listen": "test",
              "script": {
                "exec": [
                  "pm.test('Status code is 200', function () { pm.response.to.have.status(200); });"
                ],
                "type": "text/javascript"
              }
            }
          ],
          "request": {
            "method": "GET",
            "header": [],
            "url": {
              "raw": "http://localhost:3000/api/pedidos-snacks/mis-pedidos",
              "protocol": "http",
              "host": [
                "localhost"
              ],
              "port": "3000",
              "path": [
                "api",
                "pedidos-snacks",
                "mis-pedidos"
              ]
            }
          },
          "response": []
        },
        {
          "name": "Crear Pedido",
          "event": [
            {
              "listen": "test",
              "script": {
                "exec": [
                  "pm.test('Status code is 201', function () { pm.response.to.have.status(201); });"
                ],
                "type": "text/javascript",
                "packages": {},
                "requests": {}
              }
            }
          ],
          "request": {
            "method": "POST",
            "header": [],
            "body": {
              "mode": "raw",
              "raw": "{\n    \"reserva_id\": \"69bc6e73abaefb3b79b2417a\",\n    \"items\": [\n        {\n            \"snack_id\": \"69bc6f52abaefb3b79b2419f\",\n            \"cantidad\": 2\n        }\n    ]\n}",
              "options": {
                "raw": {
                  "language": "json"
                }
              }
            },
            "url": {
              "raw": "http://localhost:3000/api/pedidos-snacks",
              "protocol": "http",
              "host": [
                "localhost"
              ],
              "port": "3000",
              "path": [
                "api",
                "pedidos-snacks"
              ]
            }
          },
          "response": []
        },
        {
          "name": "Listar Todos Pedidos",
          "event": [
            {
              "listen": "test",
              "script": {
                "exec": [
                  "pm.test('Status code is 200', function () { pm.response.to.have.status(200); });"
                ],
                "type": "text/javascript"
              }
            }
          ],
          "request": {
            "method": "GET",
            "header": [],
            "url": {
              "raw": "http://localhost:3000/api/pedidos-snacks",
              "protocol": "http",
              "host": [
                "localhost"
              ],
              "port": "3000",
              "path": [
                "api",
                "pedidos-snacks"
              ]
            }
          },
          "response": []
        },
        {
          "name": "Obtener Pedido",
          "event": [
            {
              "listen": "test",
              "script": {
                "exec": [
                  "pm.test('Status code is 200', function () { pm.response.to.have.status(200); });"
                ],
                "type": "text/javascript"
              }
            }
          ],
          "request": {
            "method": "GET",
            "header": [],
            "url": {
              "raw": "http://localhost:3000/api/pedidos-snacks/ID_AQUI",
              "protocol": "http",
              "host": [
                "localhost"
              ],
              "port": "3000",
              "path": [
                "api",
                "pedidos-snacks",
                "ID_AQUI"
              ]
            }
          },
          "response": []
        },
        {
          "name": "Actualizar Estado Pedido",
          "event": [
            {
              "listen": "test",
              "script": {
                "exec": [
                  "pm.test('Status code is 200', function () { pm.response.to.have.status(200); });"
                ],
                "type": "text/javascript"
              }
            }
          ],
          "request": {
            "method": "PUT",
            "header": [],
            "body": {
              "mode": "raw",
              "raw": "{\n    \"estado\": \"Entregado\"\n}",
              "options": {
                "raw": {
                  "language": "json"
                }
              }
            },
            "url": {
              "raw": "http://localhost:3000/api/pedidos-snacks/ID_AQUI",
              "protocol": "http",
              "host": [
                "localhost"
              ],
              "port": "3000",
              "path": [
                "api",
                "pedidos-snacks",
                "ID_AQUI"
              ]
            }
          },
          "response": []
        }
      ]
    },
    {
      "name": "Base Route",
      "event": [
        {
          "listen": "test",
          "script": {
            "exec": [
              "pm.test('Status code is 200', function () { pm.response.to.have.status(200); });"
            ],
            "type": "text/javascript"
          }
        }
      ],
      "request": {
        "method": "GET",
        "header": [],
        "url": {
          "raw": "http://localhost:3000/api",
          "protocol": "http",
          "host": [
            "localhost"
          ],
          "port": "3000",
          "path": [
            "api"
          ]
        }
      },
      "response": []
    }
  ],
  "auth": {
    "type": "bearer",
    "bearer": [
      {
        "key": "token",
        "value": "eyJhbGciOiJIUzI1NiIsInR5cCI6IkpXVCJ9.eyJpZCI6IjY5YmM2OWQwNzRlNzYzMTMxY2NiNjI2MyIsImlhdCI6MTc3Mzk1NTUzNywiZXhwIjoxNzc0MDQxOTM3fQ.KUKIgiCKptWJ5W-Em_h6q3G_ocwpfaEggE7eZIml36Y",
        "type": "string"
      }
    ]
  },
  "event": [
    {
      "listen": "prerequest",
      "script": {
        "type": "text/javascript",
        "packages": {},
        "requests": {},
        "exec": [
          ""
        ]
      }
    },
    {
      "listen": "test",
      "script": {
        "type": "text/javascript",
        "packages": {},
        "requests": {},
        "exec": [
          ""
        ]
      }
    }
  ]
}